libfiat/__init__.py
libfiat/client.py
libfiat/driver.py
libfiat/util.py
libfiat-0.1.3.dist-info/METADATA
libfiat-0.1.3.dist-info/WHEEL
libfiat-0.1.3.dist-info/RECORD
