Metadata-Version: 2.4
Name: libfiat
Version: 0.1.3
Summary: A Python 3 client for interacting with FIAT-based firmware
Project-URL: homepage, https://github.com/danpage/fiat
Project-URL: documentation, https://fiat.readthedocs.io
Maintainer-email: Daniel Page <dan@phoo.org>
License: MIT License
Classifier: Development Status :: 4 - Beta
Classifier: License :: OSI Approved :: MIT License
Classifier: Operating System :: OS Independent
Classifier: Programming Language :: Python :: 3
Requires-Python: >=3.8
Requires-Dist: crc
Requires-Dist: pyserial
